cloudcat/__init__.py
cloudcat/cli.py
cloudcat/compression.py
cloudcat/config.py
cloudcat/filtering.py
cloudcat/formatters.py
cloudcat/progress.py
cloudcat/readers/__init__.py
cloudcat/readers/avro.py
cloudcat/readers/csv.py
cloudcat/readers/json.py
cloudcat/readers/orc.py
cloudcat/readers/parquet.py
cloudcat/readers/text.py
cloudcat/storage/__init__.py
cloudcat/storage/azure.py
cloudcat/storage/base.py
cloudcat/storage/gcs.py
cloudcat/storage/s3.py
cloudcat/streaming/__init__.py
cloudcat/streaming/filesystems.py
cloudcat/streaming/stats.py
cloudcat/streaming/tracking.py
cloudcat-0.3.8.dist-info/licenses/LICENSE
tests/__init__.py
tests/conftest.py
tests/test_cli.py
tests/test_compression.py
tests/test_config.py
tests/test_data_reading.py
tests/test_file_filtering.py
tests/test_filtering.py
tests/test_format_detection.py
tests/test_integration.py
tests/test_output_formatting.py
tests/test_path_parsing.py
cloudcat-0.3.8.dist-info/METADATA
cloudcat-0.3.8.dist-info/WHEEL
cloudcat-0.3.8.dist-info/entry_points.txt
cloudcat-0.3.8.dist-info/top_level.txt
cloudcat-0.3.8.dist-info/RECORD
