Metadata-Version: 2.4
Name: cloudcat
Version: 0.3.8
Summary: Preview and analyze data files in Google Cloud Storage, AWS S3, and Azure Data Lake Storage Gen2 from your terminal
Home-page: https://github.com/jonathansudhakar1/cloudcat
Author: Jonathan Sudhakar
Author-email: jonathan@example.com
Project-URL: Homepage, https://github.com/jonathansudhakar1/cloudcat
Project-URL: Documentation, https://cloudcatcli.com
Project-URL: Bug Reports, https://github.com/jonathansudhakar1/cloudcat/issues
Project-URL: Source, https://github.com/jonathansudhakar1/cloudcat
Keywords: cloud,gcs,s3,azure,cli,storage,data,parquet,csv,json,avro,orc,google-cloud,aws,adls,datalake,data-engineering,etl,spark,bigquery,databricks,kafka,hive
Classifier: Development Status :: 4 - Beta
Classifier: Intended Audience :: Developers
Classifier: Intended Audience :: System Administrators
Classifier: Intended Audience :: Science/Research
Classifier: Topic :: Utilities
Classifier: Topic :: Database
Classifier: Topic :: Scientific/Engineering :: Information Analysis
Classifier: Topic :: System :: Systems Administration
Classifier: Environment :: Console
Classifier: License :: OSI Approved :: MIT License
Classifier: Operating System :: OS Independent
Classifier: Programming Language :: Python :: 3
Classifier: Programming Language :: Python :: 3.7
Classifier: Programming Language :: Python :: 3.8
Classifier: Programming Language :: Python :: 3.9
Classifier: Programming Language :: Python :: 3.10
Classifier: Programming Language :: Python :: 3.11
Classifier: Programming Language :: Python :: 3.12
Classifier: Programming Language :: Python :: 3.13
Requires-Python: >=3.7
License-File: LICENSE
Requires-Dist: click>=8.0.0
Requires-Dist: pandas>=1.3.0
Requires-Dist: tabulate>=0.8.9
Requires-Dist: colorama>=0.4.4
Requires-Dist: google-cloud-storage>=2.0.0
Requires-Dist: boto3>=1.18.0
Requires-Dist: azure-storage-file-datalake>=12.0.0
Requires-Dist: azure-identity>=1.0.0
Provides-Extra: parquet
Requires-Dist: pyarrow>=5.0.0; extra == "parquet"
Provides-Extra: avro
Requires-Dist: fastavro>=1.4.0; extra == "avro"
Provides-Extra: orc
Requires-Dist: pyarrow>=5.0.0; extra == "orc"
Provides-Extra: zstd
Requires-Dist: zstandard>=0.15.0; extra == "zstd"
Provides-Extra: lz4
Requires-Dist: lz4>=3.0.0; extra == "lz4"
Provides-Extra: snappy
Requires-Dist: python-snappy>=0.6.0; extra == "snappy"
Provides-Extra: compression
Requires-Dist: zstandard>=0.15.0; extra == "compression"
Requires-Dist: lz4>=3.0.0; extra == "compression"
Requires-Dist: python-snappy>=0.6.0; extra == "compression"
Provides-Extra: all
Requires-Dist: pyarrow>=5.0.0; extra == "all"
Requires-Dist: fastavro>=1.4.0; extra == "all"
Requires-Dist: zstandard>=0.15.0; extra == "all"
Requires-Dist: lz4>=3.0.0; extra == "all"
Requires-Dist: python-snappy>=0.6.0; extra == "all"
Dynamic: author
Dynamic: author-email
Dynamic: classifier
Dynamic: description
Dynamic: description-content-type
Dynamic: home-page
Dynamic: keywords
Dynamic: license-file
Dynamic: project-url
Dynamic: provides-extra
Dynamic: requires-dist
Dynamic: requires-python
Dynamic: summary
